cnum/__init__.py
cnum-0.0.6.dist-info/LICENSE
cnum-0.0.6.dist-info/METADATA
cnum-0.0.6.dist-info/WHEEL
cnum-0.0.6.dist-info/top_level.txt
cnum-0.0.6.dist-info/RECORD
