Metadata-Version: 2.1
Name: cnum
Version: 0.0.6
Summary: Change int and float value to Chinese numeral format string
Home-page: https://github.com/town-paddy/cnum
Author: town_paddy
Author-email: town_paddy@yahoo.com
Project-URL: website, https://sites.google.com/view/kumake/english
Project-URL: twitter, https://twitter.com/tweet_paddy
Classifier: Programming Language :: Python :: 3
Classifier: License :: OSI Approved :: MIT License
Classifier: Operating System :: OS Independent
Requires-Python: >=3.6
License-File: LICENSE
